some.py
some-2.0.dist-info/LICENSE
some-2.0.dist-info/METADATA
some-2.0.dist-info/WHEEL
some-2.0.dist-info/entry_points.txt
some-2.0.dist-info/top_level.txt
some-2.0.dist-info/RECORD
