Metadata-Version: 2.1
Name: some
Version: 2.0
Summary: More than less; less than more.
Home-page: https://github.com/sersorrel/some
Author: Ash Holland
Author-email: ash@sorrel.sh
License: EUPL-1.2
Keywords: pager
Platform: UNKNOWN
Classifier: Development Status :: 5 - Production/Stable
Classifier: Environment :: Console
Classifier: License :: OSI Approved :: European Union Public Licence 1.2 (EUPL 1.2)
Classifier: Programming Language :: Python :: 3
Classifier: Programming Language :: Python :: 3.6
Requires-Python: >=3.6
